fluxer/__init__.py
fluxer/cli.py
fluxer/templates/api.py.txt
fluxer/templates/parser.py.txt
fluxer-0.2.1.dist-info/METADATA
fluxer-0.2.1.dist-info/WHEEL
fluxer-0.2.1.dist-info/entry_points.txt
fluxer-0.2.1.dist-info/top_level.txt
fluxer-0.2.1.dist-info/RECORD
