Metadata-Version: 2.4
Name: fluxer
Version: 0.2.1
Summary: Fluxer — a high-performance toolkit for advanced workflow management in Python.
Author: mintaru
License: MIT
Requires-Python: >=3.8
